Wrapper_Weather_Module_V1/__init__.py
Wrapper_Weather_Module_V1/main.py
Wrapper_Weather_Module_V1/functions/__init__.py
Wrapper_Weather_Module_V1/functions/functions.py
Wrapper_Weather_Module_V1-0.0.1.dist-info/METADATA
Wrapper_Weather_Module_V1-0.0.1.dist-info/WHEEL
Wrapper_Weather_Module_V1-0.0.1.dist-info/top_level.txt
Wrapper_Weather_Module_V1-0.0.1.dist-info/RECORD
